pyopnsense/__init__.py
pyopnsense/backup.py
pyopnsense/client.py
pyopnsense/diagnostics.py
pyopnsense/exceptions.py
pyopnsense/firewall.py
pyopnsense/firmware.py
pyopnsense/routes.py
pyopnsense/tests/__init__.py
pyopnsense/tests/base.py
pyopnsense/tests/test_client.py
pyopnsense-0.4.0.dist-info/AUTHORS
pyopnsense-0.4.0.dist-info/LICENSE
pyopnsense-0.4.0.dist-info/METADATA
pyopnsense-0.4.0.dist-info/WHEEL
pyopnsense-0.4.0.dist-info/pbr.json
pyopnsense-0.4.0.dist-info/top_level.txt
pyopnsense-0.4.0.dist-info/RECORD
