Metadata-Version: 2.1
Name: pyopnsense
Version: 0.4.0
Summary: A python API client for OPNsense
Author: Matthew Treinish
Author-email: mtreinish@kortar.org
Classifier: License :: OSI Approved :: GNU General Public License v3 (GPLv3)
Classifier: Programming Language :: Python
Classifier: Programming Language :: Python :: 3
Classifier: Programming Language :: Python :: 3.8
Classifier: Programming Language :: Python :: 3.9
Classifier: Programming Language :: Python :: 3.10
Classifier: Programming Language :: Python :: 3.11
Requires-Python: >=3.8
License-File: LICENSE
License-File: AUTHORS
Requires-Dist: pbr (>=1.6)
Requires-Dist: requests (>=2.14.2)
